_elperiodic.cpython-39-aarch64-linux-gnu.so
elperiodic/ElPeriodic.py
elperiodic/__init__.py
elperiodic-1.5.1.dist-info/METADATA
elperiodic-1.5.1.dist-info/WHEEL
elperiodic-1.5.1.dist-info/top_level.txt
elperiodic-1.5.1.dist-info/RECORD
elperiodic-1.5.1.dist-info/licenses/AUTHORS
elperiodic-1.5.1.dist-info/licenses/COPYING
