Metadata-Version: 2.4
Name: ElPeriodic
Version: 1.5.1
Summary: Phase-locked userland scheduling library
Home-page: https://github.com/sobomax/libelperiodic
Author: Maksym Sobolyev
Author-email: sobomax@gmail.com
License: BSD-2-Clause
Classifier: Operating System :: POSIX
Classifier: Programming Language :: C
Classifier: Programming Language :: Python
Requires-Python: >=2.7
License-File: COPYING
License-File: AUTHORS
Dynamic: author
Dynamic: author-email
Dynamic: classifier
Dynamic: description
Dynamic: description-content-type
Dynamic: home-page
Dynamic: license
Dynamic: license-file
Dynamic: requires-python
Dynamic: summary
